comic_home_api/__init__.py
comic_home_api/comic_home_api.py
comic_home_api-0.1.0.dist-info/LICENSE
comic_home_api-0.1.0.dist-info/WHEEL
comic_home_api-0.1.0.dist-info/METADATA
comic_home_api-0.1.0.dist-info/RECORD
