Metadata-Version: 2.1
Name: comic-home-api
Version: 0.1.0
Summary: A comic home api package.
License: MIT
Author: Hongbo Liu
Requires-Python: >=3.8,<4.0
Classifier: License :: OSI Approved :: MIT License
Classifier: Programming Language :: Python :: 3
Classifier: Programming Language :: Python :: 3.8
Classifier: Programming Language :: Python :: 3.9
Classifier: Programming Language :: Python :: 3.10
Classifier: Programming Language :: Python :: 3.11
